vosk_tts/__init__.py
vosk_tts/cli.py
vosk_tts/g2p.py
vosk_tts/model.py
vosk_tts/synth.py
vosk_tts-0.3.61.dist-info/LICENSE
vosk_tts-0.3.61.dist-info/METADATA
vosk_tts-0.3.61.dist-info/WHEEL
vosk_tts-0.3.61.dist-info/entry_points.txt
vosk_tts-0.3.61.dist-info/top_level.txt
vosk_tts-0.3.61.dist-info/RECORD
