Metadata-Version: 2.1
Name: vosk-tts
Version: 0.3.61
Summary: Offline text to speech synthesis
Home-page: https://github.com/alphacep/vosk-tts
Author: Alpha Cephei Inc
Author-email: contact@alphacephei.com
Classifier: Programming Language :: Python :: 3
Classifier: License :: OSI Approved :: Apache Software License
Classifier: Operating System :: Microsoft :: Windows
Classifier: Operating System :: POSIX :: Linux
Classifier: Operating System :: MacOS :: MacOS X
Classifier: Topic :: Software Development :: Libraries :: Python Modules
Requires-Python: >=3.7
License-File: LICENSE
Requires-Dist: onnxruntime (>=1.14)
Requires-Dist: requests
Requires-Dist: tokenizers
Requires-Dist: tqdm
